cockroach/__init__.py
cockroach/developing_cockroach.py
Developing_Cockroach-0.4.1.dist-info/LICENSE
Developing_Cockroach-0.4.1.dist-info/METADATA
Developing_Cockroach-0.4.1.dist-info/WHEEL
Developing_Cockroach-0.4.1.dist-info/top_level.txt
Developing_Cockroach-0.4.1.dist-info/RECORD
